<?xml version="1.0" encoding="UTF-8"?>
<geoname>
   <toponymName>Providence</toponymName>
   <name>Providence</name>
   <lat>41.82399</lat>
   <lng>-71.41283</lng>
   <geonameId>5224151</geonameId>
   <countryCode>US</countryCode>
   <countryName>United States</countryName>
   <fcl>P</fcl>
   <fcode>PPLA</fcode>
   <fclName>city, village,...</fclName>
   <fcodeName>seat of a first-order administrative division</fcodeName>
   <population>179207</population>
   <asciiName>Providence</asciiName>
   <alternateNames>Gorad Providehns,PVD,Provedensos,Provid"ns,Providence,Providens,Providensa,Providensas,Providentia,Provintens,Provėdensos,brwfydns,peulobideonseu,phr x wi den s,piravitens,prabhidensa,pravidens,prawydns,probhidensa,provhidansa,prwbydns,prwwyڈns  rwڈ aylynڈ,pu luo wei deng si,pu luo wei dun si,purobidensu,purovu~idensu,Πρόβιντενς,Горад Провідэнс,Провиденс,Провидънс,Провіденс,Փրովիդենս,פראווידענס,פרובידנס,بروفيدنس,پراویدنس,پروویڈنس,پروویڈنس، روڈ آئلینڈ,प्रभिदेन्स,प्राविडेन्स्,प्रॉव्हिडन्स,प्रोभिडेन्स,பிராவிடென்ஸ்,พรอวิเดนซ์,プロビデンス,プロヴィデンス,普洛威頓斯,普罗维登斯,프로비던스</alternateNames>
   <elevation>2</elevation>
   <srtm3>-17</srtm3>
   <astergdem>25</astergdem>
   <continentCode>NA</continentCode>
   <adminCode1 ISO3166-2="RI">RI</adminCode1>
   <adminName1>Rhode Island</adminName1>
   <adminCode2>007</adminCode2>
   <adminName2>Providence County</adminName2>
   <adminCode3>59000</adminCode3>
   <adminName3>City of Providence</adminName3>
   <alternateName lang="ko">프로비던스</alternateName>
   <alternateName lang="ja">プロビデンス</alternateName>
   <alternateName lang="ja">プロヴィデンス</alternateName>
   <alternateName lang="th">พรอวิเดนซ์</alternateName>
   <alternateName lang="post">02901</alternateName>
   <alternateName lang="post">02902</alternateName>
   <alternateName lang="post">02903</alternateName>
   <alternateName lang="post">02904</alternateName>
   <alternateName lang="post">02905</alternateName>
   <alternateName lang="post">02906</alternateName>
   <alternateName lang="post">02907</alternateName>
   <alternateName lang="post">02908</alternateName>
   <alternateName lang="post">02909</alternateName>
   <alternateName lang="post">02912</alternateName>
   <alternateName lang="post">02918</alternateName>
   <alternateName lang="post">02940</alternateName>
   <alternateName lang="link">http://en.wikipedia.org/wiki/Providence%2C_Rhode_Island</alternateName>
   <alternateName lang="link">http://ru.wikipedia.org/wiki/%D0%9F%D1%80%D0%BE%D0%B2%D0%B8%D0%B4%D0%B5%D0%BD%D1%81_%28%D0%A0%D0%BE%D0%B4-%D0%90%D0%B9%D0%BB%D0%B5%D0%BD%D0%B4%29</alternateName>
   <alternateName lang="sgs">Provėdensos</alternateName>
   <alternateName lang="da">Providence</alternateName>
   <alternateName lang="de">Providence</alternateName>
   <alternateName isPreferredName="true" lang="en">Providence</alternateName>
   <alternateName lang="eo">Providence</alternateName>
   <alternateName lang="es">Providence</alternateName>
   <alternateName lang="eu">Providence</alternateName>
   <alternateName lang="fi">Providence</alternateName>
   <alternateName lang="fr">Providence</alternateName>
   <alternateName lang="id">Providence</alternateName>
   <alternateName lang="io">Providence</alternateName>
   <alternateName lang="it">Providence</alternateName>
   <alternateName lang="nl">Providence</alternateName>
   <alternateName lang="no">Providence</alternateName>
   <alternateName lang="oc">Providence</alternateName>
   <alternateName lang="pl">Providence</alternateName>
   <alternateName lang="pt">Providence</alternateName>
   <alternateName lang="sk">Providence</alternateName>
   <alternateName lang="sv">Providence</alternateName>
   <alternateName lang="lv">Providensa</alternateName>
   <alternateName lang="lt">Providensas</alternateName>
   <alternateName lang="la">Providentia</alternateName>
   <alternateName lang="iata">PVD</alternateName>
   <alternateName lang="ar">بروفيدنس</alternateName>
   <alternateName lang="fa">پراویدنس</alternateName>
   <alternateName lang="pnb">پروویڈنس</alternateName>
   <alternateName lang="ur">پروویڈنس، روڈ آئلینڈ</alternateName>
   <alternateName lang="yi">פראווידענס</alternateName>
   <alternateName lang="he">פרובידנס</alternateName>
   <alternateName lang="el">Πρόβιντενς</alternateName>
   <alternateName lang="be">Горад Провідэнс</alternateName>
   <alternateName lang="ky">Провиденс</alternateName>
   <alternateName lang="mk">Провиденс</alternateName>
   <alternateName lang="mrj">Провиденс</alternateName>
   <alternateName lang="ru">Провиденс</alternateName>
   <alternateName lang="sr">Провиденс</alternateName>
   <alternateName lang="bg">Провидънс</alternateName>
   <alternateName lang="uk">Провіденс</alternateName>
   <alternateName lang="hy">Փրովիդենս</alternateName>
   <alternateName lang="new">प्रभिदेन्स</alternateName>
   <alternateName lang="sa">प्राविडेन्स्</alternateName>
   <alternateName lang="mr">प्रॉव्हिडन्स</alternateName>
   <alternateName lang="pi">प्रोभिडेन्स</alternateName>
   <alternateName lang="ta">பிராவிடென்ஸ்</alternateName>
   <alternateName lang="zh-TW">普洛威頓斯</alternateName>
   <alternateName lang="zh">普罗维登斯</alternateName>
   <timezone dstOffset="-4.0" gmtOffset="-5.0">America/New_York</timezone>
   <bbox>
      <west>-71.47267</west>
      <north>41.86157</north>
      <east>-71.36969</east>
      <south>41.77241</south>
      <accuracyLevel>0</accuracyLevel>
   </bbox>
</geoname>
