<?xml version="1.0" encoding="UTF-8"?>
<geoname>
   <toponymName>Acre</toponymName>
   <name>Acre</name>
   <lat>-9</lat>
   <lng>-70</lng>
   <geonameId>3665474</geonameId>
   <countryCode>BR</countryCode>
   <countryName>Brazil</countryName>
   <fcl>A</fcl>
   <fcode>ADM1</fcode>
   <fclName>country, state, region,...</fclName>
   <fcodeName>first-order administrative division</fcodeName>
   <population>732793</population>
   <asciiName>Acre</asciiName>
   <alternateNames>AC,Acre,Estado de Acre,Estado do Acre,Territorio Federal do Acre,Territorio do Acre,Território Federal do Acre</alternateNames>
   <elevation/>
   <srtm3>234</srtm3>
   <astergdem>229</astergdem>
   <continentCode>SA</continentCode>
   <adminCode1 ISO3166-2="AC">01</adminCode1>
   <adminTypeName>state</adminTypeName>
   <adminName1>Acre</adminName1>
   <adminCode2/>
   <adminName2/>
   <alternateName lang="abbr">AC</alternateName>
   <alternateName isShortName="true" lang="es">Acre</alternateName>
   <alternateName lang="pt">Acre</alternateName>
   <alternateName>Acre</alternateName>
   <alternateName isPreferredName="true" lang="es">Estado de Acre</alternateName>
   <alternateName>Estado do Acre</alternateName>
   <alternateName lang="link">http://en.wikipedia.org/wiki/Acre_(state)</alternateName>
   <alternateName lang="link">http://id.loc.gov/authorities/names/n80113129</alternateName>
   <alternateName>Territorio do Acre</alternateName>
   <alternateName>Território Federal do Acre</alternateName>
   <timezone dstOffset="-5.0" gmtOffset="-5.0">America/Rio_Branco</timezone>
   <bbox>
      <west>-73.99045</west>
      <north>-7.11182</north>
      <east>-66.62384</east>
      <south>-11.14556</south>
      <accuracyLevel>0</accuracyLevel>
   </bbox>
</geoname>
