<?xml version="1.0" encoding="UTF-8"?>
<geoname>
   <toponymName>São Paulo</toponymName>
   <name>São Paulo</name>
   <lat>-23.5475</lat>
   <lng>-46.63611</lng>
   <geonameId>3448439</geonameId>
   <countryCode>BR</countryCode>
   <countryName>Brazil</countryName>
   <fcl>P</fcl>
   <fcode>PPLA</fcode>
   <fclName>city, village,...</fclName>
   <fcodeName>seat of a first-order administrative division</fcodeName>
   <population>10021295</population>
   <asciiName>Sao Paulo</asciiName>
   <alternateNames>SAO,Sampa,San Paolo,San Paul ed Brasil,San Paulas,San Paulo,San Paulu,San Paulu du Brasili,San Paulu dû Brasili,San Pauluw,San Pawlo,San Polo del Braxil,San Poulo,San Poło del Braxil,San Pàul ëd Brasil,San-Paulo,San-Paulu,San-Paŭlo,Sanpaulu,Sao Paolo,Sao Paulo,Sao Paulo capital,Saun Paulu,Sawo Palo,Sawo Pålo,São Paolo,São Paulo,São Paulo capital,Urbs Paulistana,cavo pavulo,sa'o pa'ulo,sa'o paulo,samu pa'ulu,sangpaollo,sangpaollu,sangpaullo,sangpaullu,sankt. paulos,sanpauro,savea pealea,savo palo,saw bawlw,saw palw,saw pwlw,saywpaywlw,sea pea lu,sheng bao luo,Σάο Πάολο,Сан Пауло,Сан Паулу,Сан-Паулу,Сан-Паўлу,Сао Паоло,Сао Пауло,Սան Պաուլու,סאו פאולא,סאו פאולו,ساؤ پالو,ساؤ پولو,سائوپائولو,ساو باولو,ܣܐܘ ܦܐܘܠܘ,ސައޮ ޕައުލޯ,साओ पाउलो,সাঁউ পাউলু,সাও পাউলো,சாவோ பாவுலோ,శఒ పౌలొ,ಸಾವೊ ಪಾಲೊ,സാവോ പോളോ,เซาเปาลู,ဆောပိုလိုမြို့,სან-პაულუ,ሳው ፓውሉ,サンパウロ,聖保羅,상파올로,상파올루,상파울로,상파울루</alternateNames>
   <elevation/>
   <srtm3>769</srtm3>
   <astergdem>759</astergdem>
   <continentCode>SA</continentCode>
   <adminCode1 ISO3166-2="SP">27</adminCode1>
   <adminName1>São Paulo</adminName1>
   <adminCode2>3550308</adminCode2>
   <adminName2>São Paulo</adminName2>
   <alternateName lang="am">ሳው ፓውሉ</alternateName>
   <alternateName lang="arc">ܣܐܘ ܦܐܘܠܘ</alternateName>
   <alternateName lang="dv">ސައޮ ޕައުލޯ</alternateName>
   <alternateName lang="ko">상파올로</alternateName>
   <alternateName lang="ko">상파올루</alternateName>
   <alternateName lang="ko">상파울로</alternateName>
   <alternateName isPreferredName="true" lang="ko">상파울루</alternateName>
   <alternateName lang="ja">サンパウロ</alternateName>
   <alternateName lang="th">เซาเปาลู</alternateName>
   <alternateName lang="link">http://en.wikipedia.org/wiki/S%C3%A3o_Paulo</alternateName>
   <alternateName lang="link">http://id.loc.gov/authorities/names/n79077404</alternateName>
   <alternateName lang="link">http://ru.wikipedia.org/wiki/%D0%A1%D0%B0%D0%BD-%D0%9F%D0%B0%D1%83%D0%BB%D1%83</alternateName>
   <alternateName isColloquial="true" lang="pt">Sampa</alternateName>
   <alternateName lang="jbo">sankt. paulos</alternateName>
   <alternateName lang="it">San Paolo</alternateName>
   <alternateName lang="lt">San Paulas</alternateName>
   <alternateName lang="pms">San Pàul ëd Brasil</alternateName>
   <alternateName lang="gl">San Paulo</alternateName>
   <alternateName>San Paulo</alternateName>
   <alternateName lang="eo">San-Paŭlo</alternateName>
   <alternateName lang="lv">Sanpaulu</alternateName>
   <alternateName lang="crh">San Paulu</alternateName>
   <alternateName lang="nrm">San Paulu</alternateName>
   <alternateName lang="tpi">San Paulu</alternateName>
   <alternateName lang="uz">San Paulu</alternateName>
   <alternateName lang="tk">San-Paulu</alternateName>
   <alternateName lang="scn">San Paulu dû Brasili</alternateName>
   <alternateName lang="ay">San Pauluw</alternateName>
   <alternateName lang="ug">San Pawlo</alternateName>
   <alternateName lang="vec">San Poło del Braxil</alternateName>
   <alternateName lang="mwl">San Poulo</alternateName>
   <alternateName lang="iata">SAO</alternateName>
   <alternateName lang="ht">São Paolo</alternateName>
   <alternateName lang="bs">Sao Paulo</alternateName>
   <alternateName lang="eu">Sao Paulo</alternateName>
   <alternateName lang="hbs">Sao Paulo</alternateName>
   <alternateName lang="io">Sao Paulo</alternateName>
   <alternateName lang="sc">Sao Paulo</alternateName>
   <alternateName lang="tr">Sao Paulo</alternateName>
   <alternateName lang="af">São Paulo</alternateName>
   <alternateName lang="ca">São Paulo</alternateName>
   <alternateName lang="co">São Paulo</alternateName>
   <alternateName lang="cs">São Paulo</alternateName>
   <alternateName lang="da">São Paulo</alternateName>
   <alternateName lang="de">São Paulo</alternateName>
   <alternateName isPreferredName="true" lang="en">São Paulo</alternateName>
   <alternateName lang="es">São Paulo</alternateName>
   <alternateName lang="et">São Paulo</alternateName>
   <alternateName lang="fi">São Paulo</alternateName>
   <alternateName lang="fr">São Paulo</alternateName>
   <alternateName lang="ga">São Paulo</alternateName>
   <alternateName lang="hu">São Paulo</alternateName>
   <alternateName lang="id">São Paulo</alternateName>
   <alternateName lang="ms">São Paulo</alternateName>
   <alternateName lang="nl">São Paulo</alternateName>
   <alternateName lang="nn">São Paulo</alternateName>
   <alternateName lang="no">São Paulo</alternateName>
   <alternateName lang="oc">São Paulo</alternateName>
   <alternateName lang="pl">São Paulo</alternateName>
   <alternateName isPreferredName="true" lang="pt">São Paulo</alternateName>
   <alternateName lang="ro">São Paulo</alternateName>
   <alternateName lang="sk">São Paulo</alternateName>
   <alternateName lang="sv">São Paulo</alternateName>
   <alternateName lang="sw">São Paulo</alternateName>
   <alternateName lang="vi">São Paulo</alternateName>
   <alternateName lang="pt">São Paulo capital</alternateName>
   <alternateName lang="tet">Saun Paulu</alternateName>
   <alternateName lang="wa">Sawo Pålo</alternateName>
   <alternateName lang="la">Urbs Paulistana</alternateName>
   <alternateName lang="ar">ساو باولو</alternateName>
   <alternateName lang="arz">ساو باولو</alternateName>
   <alternateName lang="ur">ساؤ پالو</alternateName>
   <alternateName lang="pnb">ساؤ پولو</alternateName>
   <alternateName lang="fa">سائوپائولو</alternateName>
   <alternateName lang="mzn">سائوپائولو</alternateName>
   <alternateName lang="yi">סאו פאולא</alternateName>
   <alternateName lang="he">סאו פאולו</alternateName>
   <alternateName lang="el">Σάο Πάολο</alternateName>
   <alternateName lang="rue">Сан Пауло</alternateName>
   <alternateName lang="sah">Сан Паулу</alternateName>
   <alternateName lang="ab">Сан-Паулу</alternateName>
   <alternateName lang="ba">Сан-Паулу</alternateName>
   <alternateName lang="cv">Сан-Паулу</alternateName>
   <alternateName lang="kv">Сан-Паулу</alternateName>
   <alternateName lang="mhr">Сан-Паулу</alternateName>
   <alternateName lang="os">Сан-Паулу</alternateName>
   <alternateName isPreferredName="true" lang="ru">Сан-Паулу</alternateName>
   <alternateName lang="tg">Сан-Паулу</alternateName>
   <alternateName lang="tt">Сан-Паулу</alternateName>
   <alternateName lang="uk">Сан-Паулу</alternateName>
   <alternateName lang="xal">Сан-Паулу</alternateName>
   <alternateName isPreferredName="true" lang="be">Сан-Паўлу</alternateName>
   <alternateName lang="mk">Сао Паоло</alternateName>
   <alternateName lang="bg">Сао Пауло</alternateName>
   <alternateName lang="sr">Сао Пауло</alternateName>
   <alternateName lang="hy">Սան Պաուլու</alternateName>
   <alternateName lang="ka">სან-პაულუ</alternateName>
   <alternateName lang="hi">साओ पाउलो</alternateName>
   <alternateName lang="mr">साओ पाउलो</alternateName>
   <alternateName lang="te">శఒ పౌలొ</alternateName>
   <alternateName lang="kn">ಸಾವೊ ಪಾಲೊ</alternateName>
   <alternateName lang="ta">சாவோ பாவுலோ</alternateName>
   <alternateName lang="ml">സാവോ പോളോ</alternateName>
   <alternateName lang="bpy">সাও পাউলো</alternateName>
   <alternateName lang="bn">সাঁউ পাউলু</alternateName>
   <alternateName lang="my">ဆောပိုလိုမြို့</alternateName>
   <alternateName lang="gan">聖保羅</alternateName>
   <alternateName lang="wuu">聖保羅</alternateName>
   <alternateName lang="zh-TW">聖保羅</alternateName>
   <timezone dstOffset="-3.0" gmtOffset="-2.0">America/Sao_Paulo</timezone>
   <bbox>
      <west>-47.08299</west>
      <north>-23.13656</north>
      <east>-46.18923</east>
      <south>-23.95844</south>
      <accuracyLevel>0</accuracyLevel>
   </bbox>
</geoname>
