<?xml version="1.0" encoding="UTF-8"?><geonames style="FULL">
    <totalResultsCount>573</totalResultsCount>
    <geoname>
        <toponymName>Durham</toponymName>
        <name>Durham</name>
        <lat>18.08566</lat>
        <lng>-76.51562</lng>
        <geonameId>11495448</geonameId>
        <countryCode>JM</countryCode>
        <countryName>Jamaica</countryName>
        <fcl>A</fcl>
        <fcode>ADM2</fcode>
        <fclName>country, state, region,...</fclName>
        <fcodeName>second-order administrative division</fcodeName>
        <population>573</population>
        <adminCode1 ISO3166-2="04">07</adminCode1>
        <adminName1>Portland</adminName1>
        <asciiName>Durham</asciiName>
        <alternateNames/>
        <elevation/>
        <srtm3>349</srtm3>
        <astergdem>320</astergdem>
        <continentCode>NA</continentCode>
        <adminCode2>433</adminCode2>
        <adminName2>Durham</adminName2>
        <timezone dstOffset="-5.0" gmtOffset="-5.0">America/Jamaica</timezone>
        <bbox>
            <west>-76.56584</west>
            <north>18.16477</north>
            <east>-76.47092</east>
            <south>18.03072</south>
            <accuracyLevel>10</accuracyLevel>
        </bbox>
        <score>77.55120849609375</score>
    </geoname>
</geonames>