<?xml version="1.0" encoding="UTF-8"?>
<geonames style="FULL">
   <totalResultsCount>10</totalResultsCount>
   <geoname>
      <toponymName>Oxford</toponymName>
      <name>Oxford</name>
      <lat>34.3665</lat>
      <lng>-89.51925</lng>
      <geonameId>4440076</geonameId>
      <countryCode>US</countryCode>
      <countryName>United States</countryName>
      <fcl>P</fcl>
      <fcode>PPLA2</fcode>
      <fclName>city, village,...</fclName>
      <fcodeName>seat of a second-order administrative division</fcodeName>
      <population>22314</population>
      <asciiName>Oxford</asciiName>
      <alternateNames>Oksford,UOX,aksfwrd,aksfwrd  mysysypy,niu jin,ogseupeodeu,Оксфорд,آکسفورد، میسیسیپی,آکسفورڈ، مسیسپی,أكسفورد,牛津,옥스퍼드</alternateNames>
      <elevation>154</elevation>
      <srtm3>155</srtm3>
      <astergdem>161</astergdem>
      <continentCode>NA</continentCode>
      <adminCode1 ISO3166-2="MS">MS</adminCode1>
      <adminName1>Mississippi</adminName1>
      <adminCode2>071</adminCode2>
      <adminName2>Lafayette County</adminName2>
      <alternateName lang="ar">أكسفورد</alternateName>
      <alternateName lang="fa">آکسفورد، میسیسیپی</alternateName>
      <alternateName lang="iata">UOX</alternateName>
      <alternateName lang="kk">Оксфорд</alternateName>
      <alternateName lang="ko">옥스퍼드</alternateName>
      <alternateName lang="link">http://en.wikipedia.org/wiki/Oxford%2C_Mississippi</alternateName>
      <alternateName lang="post">38655</alternateName>
      <alternateName lang="ru">Оксфорд</alternateName>
      <alternateName lang="sr">Оксфорд</alternateName>
      <alternateName lang="unlc">USUOX</alternateName>
      <alternateName lang="ur">آکسفورڈ، مسیسپی</alternateName>
      <alternateName lang="zh">牛津</alternateName>
      <timezone dstOffset="-5.0" gmtOffset="-6.0">America/Chicago</timezone>
      <bbox>
         <west>-89.59663</west>
         <north>34.39425</north>
         <east>-89.47392</east>
         <south>34.31067</south>
         <accuracyLevel>10</accuracyLevel>
      </bbox>
      <score>44.63861083984375</score>
   </geoname>
</geonames>
