<?xml version="1.0" encoding="UTF-8"?><geoname>
    <toponymName>Poá</toponymName>
    <name>Poá</name>
    <lat>-23.52806</lat>
    <lng>-46.34472</lng>
    <geonameId>3453406</geonameId>
    <countryCode>BR</countryCode>
    <countryName>Brazil</countryName>
    <fcl>P</fcl>
    <fcode>PPL</fcode>
    <fclName>city, village,...</fclName>
    <fcodeName>populated place</fcodeName>
    <population>107432</population>
    <adminCode1 ISO3166-2="SP">27</adminCode1>
    <adminName1>São Paulo</adminName1>
    <asciiName>Poa</asciiName>
    <alternateNames/>
    <elevation/>
    <srtm3>764</srtm3>
    <astergdem>758</astergdem>
    <continentCode>SA</continentCode>
    <adminCode2>3539806</adminCode2>
    <adminName2>Poá</adminName2>
    <alternateName lang="unlc">BRPQZ</alternateName>
    <alternateName lang="link">https://en.wikipedia.org/wiki/POA</alternateName>
    <timezone dstOffset="-3.0" gmtOffset="-3.0">America/Sao_Paulo</timezone>
    <bbox>
        <west>-46.39098</west>
        <north>-23.48563</north>
        <east>-46.29847</east>
        <south>-23.57048</south>
        <accuracyLevel>0</accuracyLevel>
    </bbox>
</geoname>