<?xml version="1.0" encoding="UTF-8"?>
<geoname>
   <toponymName>Qurayyat</toponymName>
   <name>Al Qurayyat</name>
   <lat>31.33176</lat>
   <lng>37.34282</lng>
   <geonameId>108648</geonameId>
   <countryCode>SA</countryCode>
   <countryName>Saudi Arabia</countryName>
   <fcl>P</fcl>
   <fcode>PPL</fcode>
   <fclName>city, village,...</fclName>
   <fcodeName>populated place</fcodeName>
   <population>102903</population>
   <asciiName>Qurayyat</asciiName>
   <alternateNames>Al Qurayyat,Al Qurayyāt,An Nabk,An Nabk Abu Nakhlah,Gurayat,Nabek,Qurayyat,URY,alqryat,القريات</alternateNames>
   <elevation/>
   <srtm3>498</srtm3>
   <astergdem>496</astergdem>
   <continentCode>AS</continentCode>
   <adminCode1 ISO3166-2="12">20</adminCode1>
   <adminName1>Al Jawf</adminName1>
   <adminCode2>10972289</adminCode2>
   <adminName2>Al Qurayyāt</adminName2>
   <alternateName lang="en">Al Qurayyat</alternateName>
   <alternateName>Al Qurayyāt</alternateName>
   <alternateName>An Nabk</alternateName>
   <alternateName>An Nabk Abu Nakhlah</alternateName>
   <alternateName lang="en">Gurayat</alternateName>
   <alternateName lang="link">http://en.wikipedia.org/wiki/Qurayyat%2C_Saudi_Arabia</alternateName>
   <alternateName>Nabek</alternateName>
   <alternateName lang="en">Qurayyat</alternateName>
   <alternateName>Qurayyat</alternateName>
   <alternateName lang="iata">URY</alternateName>
   <alternateName lang="ar">القريات</alternateName>
   <timezone dstOffset="3.0" gmtOffset="3.0">Asia/Riyadh</timezone>
   <bbox>
      <west>37.29426</west>
      <north>31.37322</north>
      <east>37.39137</east>
      <south>31.29031</south>
      <accuracyLevel>0</accuracyLevel>
   </bbox>
</geoname>
